Metadata-Version: 2.1
Name: food-python
Version: 0.1.0
Summary: A framework for out-of-distribution and anomaly detection
Home-page: https://github.com/new-okaerinasai/food
Author: Ruslan Khaidurov, Sonya Dymchenko, Angelina Yaroshenko, Dmitry Vypirailenko
Author-email: rakhaydurov@edu.hse.ru
License: UNKNOWN
Platform: UNKNOWN
Requires-Python: >=3.6.0
